canvasapi/__init__.py
canvasapi/account.py
canvasapi/appointment_group.py
canvasapi/assignment.py
canvasapi/avatar.py
canvasapi/bookmark.py
canvasapi/calendar_event.py
canvasapi/canvas.py
canvasapi/canvas_object.py
canvasapi/conversation.py
canvasapi/course.py
canvasapi/discussion_topic.py
canvasapi/enrollment.py
canvasapi/enrollment_term.py
canvasapi/exceptions.py
canvasapi/external_tool.py
canvasapi/group.py
canvasapi/module.py
canvasapi/page.py
canvasapi/page_view.py
canvasapi/paginated_list.py
canvasapi/progress.py
canvasapi/quiz.py
canvasapi/requester.py
canvasapi/section.py
canvasapi/upload.py
canvasapi/user.py
canvasapi/util.py
canvasapi-0.3.0.dist-info/DESCRIPTION.rst
canvasapi-0.3.0.dist-info/METADATA
canvasapi-0.3.0.dist-info/RECORD
canvasapi-0.3.0.dist-info/WHEEL
canvasapi-0.3.0.dist-info/metadata.json
canvasapi-0.3.0.dist-info/top_level.txt
