Metadata-Version: 2.0
Name: canvasapi
Version: 0.3.0
Summary: API wrapper for the Canvas LMS
Home-page: https://github.com/ucfopen/canvasapi
Author: University of Central Florida - Center for Distributed Learning
Author-email: techrangers@ucf.edu
License: MIT License
Platform: UNKNOWN
Classifier: Development Status :: 3 - Alpha
Classifier: Intended Audience :: Developers
Classifier: Intended Audience :: Education
Classifier: Intended Audience :: Information Technology
Classifier: License :: OSI Approved :: MIT License
Classifier: Operating System :: OS Independent
Classifier: Programming Language :: Python
Classifier: Topic :: Software Development :: Libraries
Requires-Dist: requests
